{
  "global": {
    "red": {
      "value": "#f00",
      "type": "color"
    },
    "벚꽃": {
      "value": "#ff37c3",
      "type": "color"
    },
    "코스모스": {
      "80": {
        "value": "#e942e3cc",
        "type": "color"
      },
      "100": {
        "value": "#e942e3",
        "type": "color"
      }
    },
    "개나리": {
      "100": {
        "value": "#ffff4c",
        "type": "color"
      }
    }
  },
  "$themes": [],
  "$metadata": {
    "tokenSetOrder": [
      "global"
    ]
  }
}